nprr/__init__.py
nprr/cgf.py
nprr/dpcs.py
nprr/mechanisms.py
nprr/plotting.py
nprr/types.py
nprr-0.1.4.dist-info/LICENSE
nprr-0.1.4.dist-info/METADATA
nprr-0.1.4.dist-info/WHEEL
nprr-0.1.4.dist-info/top_level.txt
nprr-0.1.4.dist-info/RECORD
